llama_index/embeddings/isaacus/__init__.py
llama_index/embeddings/isaacus/base.py
llama_index_embeddings_isaacus-0.1.0.dist-info/METADATA
llama_index_embeddings_isaacus-0.1.0.dist-info/WHEEL
llama_index_embeddings_isaacus-0.1.0.dist-info/licenses/LICENSE
llama_index_embeddings_isaacus-0.1.0.dist-info/RECORD
