Metadata-Version: 2.4
Name: llama-index-embeddings-isaacus
Version: 0.1.0
Summary: llama-index embeddings isaacus integration
Author-email: Isaacus <hello@isaacus.com>
License-Expression: MIT
License-File: LICENSE
Requires-Python: <4.0,>=3.9
Requires-Dist: isaacus>=0.9.0
Requires-Dist: llama-index-core<0.15,>=0.13.0
